{
   "U04H4NHJC95": {
      "name": "Carson Angell",
      "slack_username": "carsonjesseangell",
      "slack_name": "carsonjesseangell",
      "personal_contact": {
         "phone_number": "3854259100",
         "school_email": "cang2135@csddocs.org",
         "personal_email": "carsonjesseangell@gmail.com"
      },
      "guardian_contact": {
         "name": "Cindy Angell",
         "phone_number": "8012093633",
         "email": "cma@westernagcredit.com"
      },
      "teams": [
         "robot.wiring",
         "robot.programming",
         "robot.build",
         "robot.design"
      ],
      "unsure_about_teams": false,
      "interested_in_outreach": true,
      "settings": {
         "recieve_push_notifications": true,
         "recieve_daily_reminders": true
      },
      "registration_stage": "Part 2 Complete"
   }
}
